pynnotator/__init__.py
pynnotator/annotator.py
pynnotator/install.py
pynnotator/main.py
pynnotator/pynnotator.py
pynnotator/settings.py
pynnotator/helpers/__init__.py
pynnotator/helpers/common.py
pynnotator/helpers/dbnsfp.bcftools.py
pynnotator/helpers/dbnsfp.cyvcf2.py
pynnotator/helpers/dbnsfp.new.py
pynnotator/helpers/dbnsfp.old.py
pynnotator/helpers/dbnsfp.py
pynnotator/helpers/dbnsfp.snpsift.py
pynnotator/helpers/decipher.py
pynnotator/helpers/func_pred.py
pynnotator/helpers/gemini.py
pynnotator/helpers/gnomad.py
pynnotator/helpers/hgmd.py
pynnotator/helpers/merge.py
pynnotator/helpers/merge.pysam.py
pynnotator/helpers/merge2.py
pynnotator/helpers/sanity_check.py
pynnotator/helpers/snpeff.py
pynnotator/helpers/snpsift.py
pynnotator/helpers/tests.py
pynnotator/helpers/validator.py
pynnotator/helpers/vcf_annotator.py
pynnotator/helpers/vcfanno.py
pynnotator/helpers/vep.py
pynnotator/helpers/vt.py
pynnotator/scripts/download_data.sh
pynnotator/scripts/header.vcf
pynnotator/scripts/install.sh
pynnotator/scripts/install_libs.py
pynnotator/scripts/install_vep.sh
pynnotator/scripts/test.py
pynnotator/scripts/vcf2csv.py
pynnotator/tests/sample.1000.vcf.gz
pynnotator/tests/test_cyvcf2.py
pynnotator/tests/test_htslib.py
pynnotator/tests/test_snpeff.py
pynnotator/tests/examples/NA12878.compound_heterozygous.vcf.gz
pynnotator/tests/examples/NA12878.dominant.vcf.gz
pynnotator/tests/examples/NA12878.recessive.vcf.gz
pynnotator/tests/examples/NA12878.xlinked.vcf.gz
pynnotator/tests/examples/miller.vcf.gz
pynnotator/tests/examples/schinzel_giedion.vcf.gz
pynnotator-2.0.dist-info/LICENSE
pynnotator-2.0.dist-info/METADATA
pynnotator-2.0.dist-info/WHEEL
pynnotator-2.0.dist-info/entry_points.txt
pynnotator-2.0.dist-info/top_level.txt
pynnotator-2.0.dist-info/RECORD
