Metadata-Version: 2.1
Name: pynnotator
Version: 2.0
Summary: A Python Annotation Framework for VCFs using multiple tools (Ex. VEP, SnpEff and SnpSift) and databases (Ex. 1000genomes, dbSNP and dbnfsp) .
Home-page: http://github.com/raonyguimaraes/pynnotator
Author: Raony Guimaraes
Author-email: raony@torchmed.com
License: BSD-3
Keywords: genome exome annotation rare diseases
Platform: UNKNOWN
Classifier: Development Status :: 4 - Beta
Classifier: Intended Audience :: Developers
Classifier: Topic :: Software Development :: Build Tools
Classifier: License :: OSI Approved :: BSD License
Classifier: Programming Language :: Python :: 2
Classifier: Programming Language :: Python :: 2.6
Classifier: Programming Language :: Python :: 2.7
Classifier: Programming Language :: Python :: 3
Classifier: Programming Language :: Python :: 3.2
Classifier: Programming Language :: Python :: 3.3
Classifier: Programming Language :: Python :: 3.4
Classifier: Programming Language :: Python :: 3.5
Classifier: Programming Language :: Python :: 3.6
Classifier: Programming Language :: Python :: 3.7
Classifier: Topic :: Scientific/Engineering :: Bio-Informatics
Requires-Dist: cython
Requires-Dist: distro
Requires-Dist: pysam
Requires-Dist: wheel
